log_translate/__init__.py
log_translate/config_default.py
log_translate/data_struct.py
log_translate/globals.py
log_translate/log_translator.py
log_translate/read_log_file.py
log_translate/ui_pyqt6.py
log_translate/ui_pyside2.py
log_translate/business/AndroidCrashPattern_translator.py
log_translate/business/__init__.py
log_translate/business/bluetooth_translator.py
log_translate/res/log_logo.ico
logtranslate-1.7.dist-info/licenses/LICENSE.txt
logtranslate-1.7.dist-info/METADATA
logtranslate-1.7.dist-info/WHEEL
logtranslate-1.7.dist-info/top_level.txt
logtranslate-1.7.dist-info/RECORD
