Metadata-Version: 2.4
Name: LogTranslate
Version: 1.7
Summary: A Python library for translate log from log files
Home-page: https://github.com/5hmlA/PyTools
Author: 5hmlA
Author-email: gene.jzy@gmail.com
License: MIT Licence
Keywords: tools log translate
Classifier: Development Status :: 3 - Alpha
Classifier: Intended Audience :: Developers
Classifier: License :: OSI Approved :: MIT License
Classifier: Programming Language :: Python :: 3.8
Classifier: Programming Language :: Python :: 3.9
Classifier: Programming Language :: Python :: 3.10
Classifier: Programming Language :: Python :: 3.11
Requires-Python: >=3.6
License-File: LICENSE.txt
Requires-Dist: PyQt6
Requires-Dist: PySide6
Requires-Dist: Rx
Requires-Dist: typer
Requires-Dist: keyboard
Requires-Dist: pyinstaller==6.2.0
Requires-Dist: qt-material
Dynamic: author
Dynamic: author-email
Dynamic: classifier
Dynamic: description
Dynamic: description-content-type
Dynamic: home-page
Dynamic: keywords
Dynamic: license
Dynamic: license-file
Dynamic: requires-dist
Dynamic: requires-python
Dynamic: summary
